mkdocs_git_latest_changes_plugin/__init__.py
mkdocs_git_latest_changes_plugin/git_adapter.py
mkdocs_git_latest_changes_plugin/helpers.py
mkdocs_git_latest_changes_plugin/models.py
mkdocs_git_latest_changes_plugin/plugin.py
mkdocs_git_latest_changes_plugin/presentation.py
mkdocs_git_latest_changes_plugin/templates/recent_changes_table.md.j2
mkdocs_git_latest_changes_plugin-0.0.23.dist-info/licenses/LICENSES/CC0-1.0.txt
mkdocs_git_latest_changes_plugin-0.0.23.dist-info/licenses/LICENSES/MIT.txt
mkdocs_git_latest_changes_plugin-0.0.23.dist-info/METADATA
mkdocs_git_latest_changes_plugin-0.0.23.dist-info/WHEEL
mkdocs_git_latest_changes_plugin-0.0.23.dist-info/entry_points.txt
mkdocs_git_latest_changes_plugin-0.0.23.dist-info/top_level.txt
mkdocs_git_latest_changes_plugin-0.0.23.dist-info/RECORD
