Metadata-Version: 2.4
Name: mkdocs-git-latest-changes-plugin
Version: 0.0.23
Summary: MkDocs plugin that allows you to display a list of recently modified pages from the Git log
Author-email: Thomas Breitner <mail@thms.de>
License: MIT License
Project-URL: Homepage, https://tombreit.github.io/mkdocs-git-latest-changes-plugin/
Project-URL: Documentation, https://github.com/tombreit/mkdocs-git-latest-changes-plugin/blob/main/README.md
Project-URL: Repository, https://github.com/tombreit/mkdocs-git-latest-changes-plugin
Project-URL: Issues, https://github.com/tombreit/mkdocs-git-latest-changes-plugin/issues
Classifier: Framework :: MkDocs
Classifier: Topic :: Documentation
Classifier: License :: OSI Approved :: MIT License
Classifier: Programming Language :: Python :: 3
Classifier: Development Status :: 3 - Alpha
Requires-Python: >=3.9
License-File: LICENSES/CC0-1.0.txt
License-File: LICENSES/MIT.txt
Requires-Dist: mkdocs>=1.5
Requires-Dist: GitPython>=3.1.43
Requires-Dist: Jinja2>=2.11.1
Provides-Extra: dev
Requires-Dist: pre-commit; extra == "dev"
Requires-Dist: reuse; extra == "dev"
Requires-Dist: mypy; extra == "dev"
Requires-Dist: ruff; extra == "dev"
Requires-Dist: pytest; extra == "dev"
Dynamic: license-file
